{
    "Type": "Graphics",
    "PassType": "Full Triangle",
    "Shader": "svgf-filter-graphics.shader",
    "Attachments": [
        {
            "Name": "Filtered Radiance Output",
            "Type": "TextureOutput",
            "Format": "rgba32float",
            "ScaleWidth": 1.0,
            "ScaleHeight": 1.0
        },
        {
            "Name": "Filtered Variance Output",
            "Type": "TextureOutput",
            "Format": "rgba32float",
            "ScaleWidth": 1.0,
            "ScaleHeight": 1.0
        },
        
        {
            "Name" : "Filtered Radiance Output",
            "Type": "TextureInput",
            "ParentJobName": "SVGF Filter 0 Graphics"
        },
        {
            "Name" : "World Position Output",
            "Type": "TextureInput",
            "ParentJobName": "Deferred Offscreen Graphics"
        },
        {
            "Name" : "Normal Output",
            "Type": "TextureInput",
            "ParentJobName": "Deferred Offscreen Graphics"
        },
        {
            "Name" : "Filtered Variance Output",
            "Type": "TextureInput",
            "ParentJobName": "SVGF Filter 0 Graphics"
        },
        {
            "Name": "Ambient Occlusion Output",
            "Type": "TextureInput",
            "ParentJobName": "Temporal Restir Graphics"
        }
    ],
    "ShaderResources": [
        { 
            "name" : "uniformData",
            "type" : "buffer",
            "size" : 2048,
            "shader_stage" : "all",
            "usage": "uniform"
        }    
    ],
    "BlendStates": [
        {
            "Enabled": "True"
        }
    ],
    "DepthStencilState":
    {
        "DepthEnable": "False",
        "DepthWriteMask": "One",
        "DepthFunc": "LessEqual",
        "StencilEnable": "False"
    },
    "RasterState":
    {
        "FillMode": "Solid",
        "CullMode": "None",
        "FrontFace": "CounterClockwise"
    }
}